dora_policy_inference/__init__.py
dora_policy_inference/__main__.py
dora_policy_inference/main.py
dora_policy_inference-0.0.0.dist-info/METADATA
dora_policy_inference-0.0.0.dist-info/WHEEL
dora_policy_inference-0.0.0.dist-info/entry_points.txt
dora_policy_inference-0.0.0.dist-info/top_level.txt
dora_policy_inference-0.0.0.dist-info/RECORD
