Metadata-Version: 2.4
Name: dora-policy-inference
Version: 0.0.0
Summary: dora-policy-inference
Author-email: Shashwat Patil <email@email.com>
License: MIT
Requires-Python: >=3.10
Requires-Dist: dora-rs>=0.3.9
Requires-Dist: pyarrow
Requires-Dist: lerobot
